{
  "palette": {
    "primary-0": "#000000",
    "primary-10": "#37003a",
    "primary-20": "#531355",
    "primary-25": "#602061",
    "primary-30": "#6e2c6e",
    "primary-35": "#7b387a",
    "primary-40": "#894587",
    "primary-50": "#a55da2",
    "primary-60": "#c177bd",
    "primary-70": "#df91d9",
    "primary-80": "#fdabf6",
    "primary-90": "#ffd6f8",
    "primary-95": "#ffebf9",
    "primary-98": "#fff7fa",
    "primary-99": "#fffbff",
    "primary-100": "#ffffff",
    "secondary-0": "#000000",
    "secondary-10": "#261625",
    "secondary-20": "#3c2b3a",
    "secondary-25": "#483646",
    "secondary-30": "#544151",
    "secondary-35": "#604c5d",
    "secondary-40": "#6d5869",
    "secondary-50": "#877083",
    "secondary-60": "#a18a9d",
    "secondary-70": "#bda4b8",
    "secondary-80": "#d9bfd3",
    "secondary-90": "#f6dbef",
    "secondary-95": "#ffebf9",
    "secondary-98": "#fff7fa",
    "secondary-99": "#fffbff",
    "secondary-100": "#ffffff",
    "tertiary-0": "#000000",
    "tertiary-10": "#321109",
    "tertiary-20": "#4c261c",
    "tertiary-25": "#593026",
    "tertiary-30": "#663b31",
    "tertiary-35": "#74473b",
    "tertiary-40": "#825247",
    "tertiary-50": "#9e6a5e",
    "tertiary-60": "#ba8376",
    "tertiary-70": "#d89d8f",
    "tertiary-80": "#f6b8a9",
    "tertiary-90": "#ffdad2",
    "tertiary-95": "#ffede9",
    "tertiary-98": "#fff8f6",
    "tertiary-99": "#fffbff",
    "tertiary-100": "#ffffff",
    "neutral-0": "#000000",
    "neutral-10": "#1e1a1d",
    "neutral-20": "#342f32",
    "neutral-25": "#3f3a3d",
    "neutral-30": "#4b4548",
    "neutral-35": "#565154",
    "neutral-40": "#635d60",
    "neutral-50": "#7c7579",
    "neutral-60": "#968f92",
    "neutral-70": "#b1a9ad",
    "neutral-80": "#cdc4c8",
    "neutral-90": "#e9e0e4",
    "neutral-95": "#f8eef2",
    "neutral-98": "#fff7fa",
    "neutral-99": "#fffbff",
    "neutral-100": "#ffffff",
    "neutral-variant-0": "#000000",
    "neutral-variant-10": "#211920",
    "neutral-variant-20": "#372e35",
    "neutral-variant-25": "#423940",
    "neutral-variant-30": "#4e444b",
    "neutral-variant-35": "#5a4f57",
    "neutral-variant-40": "#665b63",
    "neutral-variant-50": "#7f747c",
    "neutral-variant-60": "#9a8d96",
    "neutral-variant-70": "#b5a7b0",
    "neutral-variant-80": "#d1c3cc",
    "neutral-variant-90": "#eddee8",
    "neutral-variant-95": "#fcedf6",
    "neutral-variant-98": "#fff7fa",
    "neutral-variant-99": "#fffbff",
    "neutral-variant-100": "#ffffff",
    "error-0": "#000000",
    "error-10": "#410002",
    "error-20": "#690005",
    "error-25": "#7e0007",
    "error-30": "#93000a",
    "error-35": "#a80710",
    "error-40": "#ba1a1a",
    "error-50": "#de3730",
    "error-60": "#ff5449",
    "error-70": "#ff897d",
    "error-80": "#ffb4ab",
    "error-90": "#ffdad6",
    "error-95": "#ffedea",
    "error-98": "#fff8f7",
    "error-99": "#fffbff",
    "error-100": "#ffffff"
  },
  "color": {
    "primary": "#894587",
    "on-primary": "#ffffff",
    "primary-container": "#ffd6f8",
    "on-primary-container": "#37003a",
    "secondary": "#6d5869",
    "on-secondary": "#ffffff",
    "secondary-container": "#f6dbef",
    "on-secondary-container": "#261625",
    "tertiary": "#825247",
    "on-tertiary": "#ffffff",
    "tertiary-container": "#ffdad2",
    "on-tertiary-container": "#321109",
    "error": "#ba1a1a",
    "error-container": "#ffdad6",
    "on-error": "#ffffff",
    "on-error-container": "#410002",
    "background": "#fffbff",
    "on-background": "#1e1a1d",
    "surface": "#fffbff",
    "on-surface": "#1e1a1d",
    "surface-variant": "#eddee8",
    "on-surface-variant": "#4e444b",
    "outline": "#7f747c",
    "inverse-on-surface": "#f8eef2",
    "inverse-surface": "#342f32",
    "inverse-primary": "#fdabf6",
    "shadow": "#000000",
    "surface-tint": "#894587",
    "outline-variant": "#d1c3cc",
    "scrim": "#000000",
    "primary-dark": "#fdabf6",
    "on-primary-dark": "#531355",
    "primary-container-dark": "#6e2c6e",
    "on-primary-container-dark": "#ffd6f8",
    "secondary-dark": "#d9bfd3",
    "on-secondary-dark": "#3c2b3a",
    "secondary-container-dark": "#544151",
    "on-secondary-container-dark": "#f6dbef",
    "tertiary-dark": "#f6b8a9",
    "on-tertiary-dark": "#4c261c",
    "tertiary-container-dark": "#663b31",
    "on-tertiary-container-dark": "#ffdad2",
    "error-dark": "#ffb4ab",
    "error-container-dark": "#93000a",
    "on-error-dark": "#690005",
    "on-error-container-dark": "#ffdad6",
    "background-dark": "#1e1a1d",
    "on-background-dark": "#e9e0e4",
    "surface-dark": "#1e1a1d",
    "on-surface-dark": "#e9e0e4",
    "surface-variant-dark": "#4e444b",
    "on-surface-variant-dark": "#d1c3cc",
    "outline-dark": "#9a8d96",
    "inverse-on-surface-dark": "#1e1a1d",
    "inverse-surface-dark": "#e9e0e4",
    "inverse-primary-dark": "#894587",
    "shadow-dark": "#000000",
    "surface-tint-dark": "#fdabf6",
    "outline-variant-dark": "#4e444b",
    "scrim-dark": "#000000"
  }
}